conll_df/__init__.py
conll_df/conll_df.py
conll_df-0.0.3.dist-info/DESCRIPTION.rst
conll_df-0.0.3.dist-info/LICENSE.txt
conll_df-0.0.3.dist-info/METADATA
conll_df-0.0.3.dist-info/RECORD
conll_df-0.0.3.dist-info/WHEEL
conll_df-0.0.3.dist-info/metadata.json
conll_df-0.0.3.dist-info/top_level.txt
