Metadata-Version: 2.0
Name: conll-df
Version: 0.0.3
Summary: CONLL-U to Pandas DataFrame
Home-page: http://github.com/interrogator/conll-df
Author: Daniel McDonald
Author-email: mcddjx@gmail.com
License: MIT
Keywords: corpus,linguistics,nlp,treebank,parsing,conll,ud
Platform: UNKNOWN
Requires-Dist: pandas (>=0.19.2)
